carculator_utils/__init__.py
carculator_utils/array.py
carculator_utils/background_systems.py
carculator_utils/driving_cycles.py
carculator_utils/energy_consumption.py
carculator_utils/export.py
carculator_utils/hot_emissions.py
carculator_utils/inventory.py
carculator_utils/model.py
carculator_utils/noise_emissions.py
carculator_utils/particulates_emissions.py
carculator_utils/utils.py
carculator_utils/vehicle_input_parameters.py
carculator_utils/data/monthly_avg_temp.csv
carculator_utils/data/purchase_cost_params.yaml
carculator_utils/data/IAM/A_matrix.npz
carculator_utils/data/IAM/B_matrix_ef_midpoint_remind_SSP2-NPi_2005.npz
carculator_utils/data/IAM/B_matrix_ef_midpoint_remind_SSP2-NPi_2010.npz
carculator_utils/data/IAM/B_matrix_ef_midpoint_remind_SSP2-NPi_2020.npz
carculator_utils/data/IAM/B_matrix_ef_midpoint_remind_SSP2-NPi_2030.npz
carculator_utils/data/IAM/B_matrix_ef_midpoint_remind_SSP2-NPi_2040.npz
carculator_utils/data/IAM/B_matrix_ef_midpoint_remind_SSP2-NPi_2050.npz
carculator_utils/data/IAM/B_matrix_ef_midpoint_remind_SSP2-PkBudg1150_2005.npz
carculator_utils/data/IAM/B_matrix_ef_midpoint_remind_SSP2-PkBudg1150_2010.npz
carculator_utils/data/IAM/B_matrix_ef_midpoint_remind_SSP2-PkBudg1150_2020.npz
carculator_utils/data/IAM/B_matrix_ef_midpoint_remind_SSP2-PkBudg1150_2030.npz
carculator_utils/data/IAM/B_matrix_ef_midpoint_remind_SSP2-PkBudg1150_2040.npz
carculator_utils/data/IAM/B_matrix_ef_midpoint_remind_SSP2-PkBudg1150_2050.npz
carculator_utils/data/IAM/B_matrix_ef_midpoint_remind_SSP2-PkBudg500_2005.npz
carculator_utils/data/IAM/B_matrix_ef_midpoint_remind_SSP2-PkBudg500_2010.npz
carculator_utils/data/IAM/B_matrix_ef_midpoint_remind_SSP2-PkBudg500_2020.npz
carculator_utils/data/IAM/B_matrix_ef_midpoint_remind_SSP2-PkBudg500_2030.npz
carculator_utils/data/IAM/B_matrix_ef_midpoint_remind_SSP2-PkBudg500_2040.npz
carculator_utils/data/IAM/B_matrix_ef_midpoint_remind_SSP2-PkBudg500_2050.npz
carculator_utils/data/IAM/B_matrix_ef_midpoint_static.npz
carculator_utils-1.3.4.dist-info/licenses/LICENSE
carculator_utils-1.3.4.dist-info/METADATA
carculator_utils-1.3.4.dist-info/WHEEL
carculator_utils-1.3.4.dist-info/top_level.txt
carculator_utils-1.3.4.dist-info/RECORD
