Metadata-Version: 2.4
Name: carculator_utils
Version: 1.3.4
Summary: Provides convenience functions for carculator_utils
Home-page: https://github.com/romainsacchi/carculator_utils
Author: Romain Sacchi <romain.sacchi@psi.ch>
License: BSD 3-Clause License
Classifier: Intended Audience :: End Users/Desktop
Classifier: Intended Audience :: Developers
Classifier: Intended Audience :: Science/Research
Classifier: License :: OSI Approved :: BSD License
Classifier: Operating System :: MacOS :: MacOS X
Classifier: Operating System :: Microsoft :: Windows
Classifier: Operating System :: POSIX
Classifier: Programming Language :: Python
Classifier: Programming Language :: Python :: 3
Classifier: Programming Language :: Python :: 3.5
Classifier: Programming Language :: Python :: 3.6
Classifier: Programming Language :: Python :: 3.7
Classifier: Programming Language :: Python :: 3.8
Classifier: Topic :: Scientific/Engineering :: Information Analysis
Classifier: Topic :: Scientific/Engineering :: Mathematics
Classifier: Topic :: Scientific/Engineering :: Visualization
Requires-Python: >=3.10
License-File: LICENSE
Requires-Dist: pandas
Requires-Dist: xarray>=2024.1.0
Requires-Dist: numpy<2.0.0
Requires-Dist: klausen
Requires-Dist: xlrd
Requires-Dist: numexpr
Requires-Dist: bw2io<=0.8.12
Requires-Dist: pycountry
Requires-Dist: wurst
Requires-Dist: pyyaml
Dynamic: author
Dynamic: classifier
Dynamic: description
Dynamic: description-content-type
Dynamic: home-page
Dynamic: license
Dynamic: license-file
Dynamic: requires-dist
Dynamic: requires-python
Dynamic: summary
